GPAD/.gitattributes
GPAD/.gitignore
GPAD/README.md
GPAD/__init__.py
GPAD/config.xlaunch
GPAD/main.py
GPAD/requirements.txt
GPAD/vehicle_info.json
GPAD/.idea/.gitignore
GPAD/.idea/GPAD.iml
GPAD/.idea/misc.xml
GPAD/.idea/modules.xml
GPAD/.idea/vcs.xml
GPAD/.idea/workspace.xml
GPAD/.idea/inspectionProfiles/Project_Default.xml
GPAD/.idea/inspectionProfiles/profiles_settings.xml
GPAD/Approaches/__init__.py
GPAD/Approaches/Common/__init__.py
GPAD/Approaches/Common/dijkstra.py
GPAD/Approaches/Common/visibility_dubins_onepass.py
GPAD/Approaches/Common/visibility_lazy.py
GPAD/Approaches/Common/occupancy_mapper/OccupancyMapper.py
GPAD/Approaches/Common/occupancy_mapper/ReachableSetGenerator.py
GPAD/Approaches/Common/occupancy_mapper/ReachableSetPredictor.py
GPAD/Approaches/Common/occupancy_mapper/Recorder.py
GPAD/Approaches/Common/occupancy_mapper/SemanticClassifier.py
GPAD/Approaches/Common/occupancy_mapper/Tracker.py
GPAD/Approaches/Common/occupancy_mapper/VirtualVehicleGenerator.py
GPAD/Approaches/Common/occupancy_mapper/__init__.py
GPAD/Approaches/MMRIS/MMRIS.py
GPAD/Approaches/MMRIS/MMRISLauncher.py
GPAD/Approaches/MMRIS/__init__.py
GPAD/Approaches/SGSPA/SGSPA.py
GPAD/Approaches/SGSPA/SGSPALauncher.py
GPAD/Approaches/SGSPA/__init__.py
GPAD/Common/Planner.py
GPAD/Common/World.py
GPAD/Common/__init__.py
GPAD/Common/Utils/CameraManager.py
GPAD/Common/Utils/CollisionSensor.py
GPAD/Common/Utils/ControlLauncher.py
GPAD/Common/Utils/HUD.py
GPAD/Common/Utils/OccupancyViewer.py
GPAD/Common/Utils/__init__.py
GPAD/Common/Utils/carla_utils.py
GPAD/Common/Utils/controller.py
GPAD/Common/Utils/start_replaying.py
GPAD/Common/Utils/utils.py
GPAD/Common/Utils/agents/__init__.py
GPAD/Common/Utils/agents/navigation/__init__.py
GPAD/Common/Utils/agents/navigation/global_route_planner.py
GPAD/Common/Utils/agents/navigation/local_planner.py
GPAD/Common/Utils/agents/tools/__init__.py
GPAD/Common/Utils/agents/tools/misc.py
GPAD/Scenarios/apf_tuning/data.json
GPAD/Scenarios/apf_tuning/junction
gpad-0.0.1.dist-info/METADATA
gpad-0.0.1.dist-info/WHEEL
gpad-0.0.1.dist-info/licenses/LICENSE
gpad-0.0.1.dist-info/RECORD
