Metadata-Version: 2.1
Name: GPAD
Version: 0.0.1
Summary: GPAD for CARLA PythonAPI
Project-URL: Homepage, https://github.com/renaudponcelet/GPAD
Project-URL: Bug Tracker, https://github.com/renaudponcelet/GPAD/issues
Author-email: zetmus <renaud.poncelet@gmail.com>
License-File: LICENSE
Classifier: License :: OSI Approved :: MIT License
Classifier: Operating System :: OS Independent
Classifier: Programming Language :: Python :: 3
Requires-Python: >=3.7
